[  
    {
        "note":"B4",
        "colorkey":"white"
    },
    {
        "note":"A#4",
        "colorkey":"black"
    },
    {
        "note":"A4",
        "colorkey":"white"
    },
    {
        "note":"G#4",
        "colorkey":"black"
    },
    {
        "note":"G4",
        "colorkey":"white"
    },
    {
        "note":"F#4",
        "colorkey":"black"
    },
    {
        "note":"F4",
        "colorkey":"white"
    },
    {
        "note":"E4",
        "colorkey":"white"
    },
    {
        "note":"D#4",
        "colorkey":"black"
    },
    {
        "note":"D4",
        "colorkey":"white"

    },
    {
        "note":"C#4",
        "colorkey":"black"
    },
    {
        "note":"C4",
        "colorkey":"white",
        "visible":"block"
    },
    {
        "note":"B3",
        "colorkey":"white"
    },
    {
        "note":"A#3",
        "colorkey":"black"
    },
    {
        "note":"A3",
        "colorkey":"white"
    },
    {
        "note":"G#3",
        "colorkey":"black"
    },
    {
        "note":"G3",
        "colorkey":"white"
    },
    {
        "note":"F#3",
        "colorkey":"black"
    },
    {
        "note":"F3",
        "colorkey":"white"
    },
    {
        "note":"E3",
        "colorkey":"white"
    },
    {
        "note":"D#3",
        "colorkey":"black"
    },
    {
        "note":"D3",
        "colorkey":"white"

    },
    {
        "note":"C#3",
        "colorkey":"black"
    },
    {
        "note":"C3",
        "colorkey":"white",
        "visible":"block"
    },
    {
        "note":"B2",
        "colorkey":"white"
    },
    {
        "note":"A#2",
        "colorkey":"black"
    },
    {
        "note":"A2",
        "colorkey":"white"
    },
    {
        "note":"G#2",
        "colorkey":"black"
    },
    {
        "note":"G2",
        "colorkey":"white"
    },
    {
        "note":"F#2",
        "colorkey":"black"
    },
    {
        "note":"F2",
        "colorkey":"white"
    },
    {
        "note":"E2",
        "colorkey":"white"
    },
    {
        "note":"D#2",
        "colorkey":"black"
    },
    {
        "note":"D2",
        "colorkey":"white"

    },
    {
        "note":"C#2",
        "colorkey":"black"
    },
    {
        "note":"C2",
        "colorkey":"white",
        "visible":"block"
    },
    {
        "note":"B1",
        "colorkey":"white"
    },
    {
        "note":"A#1",
        "colorkey":"black"
    },
    {
        "note":"A1",
        "colorkey":"white"
    },
    {
        "note":"G#1",
        "colorkey":"black"
    },
    {
        "note":"G1",
        "colorkey":"white"
    },
    {
        "note":"F#1",
        "colorkey":"black"
    },
    {
        "note":"F1",
        "colorkey":"white"
    },
    {
        "note":"E1",
        "colorkey":"white"
    },
    {
        "note":"D#1",
        "colorkey":"black"
    },
    {
        "note":"D1",
        "colorkey":"white"

    },
    {
        "note":"C#1",
        "colorkey":"black"
    },
    {
        "note":"C1",
        "colorkey":"white",
        "visible":"block"
    }
]